<ServerManagerConfiguration>
  <!-- Begin MotionDetector -->
  <ProxyGroup name="filters">
    <SourceProxy name="MotionDetector" class="vtkMotionDetector" label="Motion Detector">
      <Documentation
        short_help="Detect motion points in lidar frame"
        long_help="Motion detector to estimate motion probability of each points in frame and to extract clusters on motion points">
        Motion detector filter estimates motion probability of points in lidar frame by building a spherical depth map with gaussian mixture model.
        It also extracts clusters on motion points and gives the information of each cluster.
      </Documentation>

    <InputProperty
      name="Input"
      port_index = "0"
      command="SetInputConnection">
      <DataTypeDomain name="input_type">
        <DataType value="vtkPolyData"/>
      </DataTypeDomain>
    </InputProperty>

    <OutputPort name="Motion detection" index="0" />
    <OutputPort name="Clusters" index="1" />
    <OutputPort name="Clusters information" index="2" />
    <Hints>
      <RepresentationType view="LidarGridView" type="Wireframe" port="1" />
      <OutputPort index="2" type="text" />
      <PipelineIcon name="SpreadSheetView" port="2" />
    </Hints>

    <!-- ============================ General ============================ -->

    <Property name="Reset detection"
              command="Reset">
      <Documentation>
        Reset motion detector. The gaussian mixture model map is clear and parameters are reset to current state. The number of
        processed frames returns to zero.
      </Documentation>
    </Property>

    <!-- ============================ Motion estimation ============================ -->
    <DoubleVectorProperty name="Detection Range"
                       command="SetDetectionRange"
                       number_of_elements="2"
                       default_values="0. 50.">
      <Documentation>
       To define the detection range. The motion detection is only applied on points that their distance from lidar is
       in the detection range [min, max].
      </Documentation>
    </DoubleVectorProperty>

    <DoubleVectorProperty name="Azimuth resolution"
                       command="SetAzimuthResolution"
                       number_of_elements="1"
                       default_values="0.1">
      <Documentation>
       Azimuth resolution should be coherent with lidar resolution.
      </Documentation>
    </DoubleVectorProperty>

    <DoubleVectorProperty name="Vertical resolution"
                       command="SetVerticalResolution"
                       number_of_elements="1"
                       default_values="1">
      <Documentation>
       Vertical angle resolution should be coherent with lidar resolution.
      </Documentation>
    </DoubleVectorProperty>

    <IntVectorProperty name="Initialization time"
                       command="SetInitializationTime"
                       number_of_elements="1"
                       default_values="100">
      <Documentation>
      The number of frames to wait for the initialization of motion detector.
      </Documentation>
    </IntVectorProperty>

    <IntVectorProperty name="Window size"
                       command="SetWindowSize"
                       number_of_elements="1"
                       default_values="100">
      <Documentation>
        It determines the duration (number of frames) a particular Gaussian component will contribute to the overall mixture model.
        A shorter window size leads to more rapid adaptation to changes in the underlying data distribution, making the model more sensitive to recent observations.
        A longer window size results in a smoother temporal evolution of the model, making it less responsive to short-term fluctuations.
      </Documentation>
    </IntVectorProperty>

    <DoubleVectorProperty name="Subsample range"
                       command="SetSubsampleRange"
                       number_of_elements="1"
                       default_values="0.">
      <Documentation>
      Subsample points.
      </Documentation>
    </DoubleVectorProperty>

    <DoubleVectorProperty name="Subsample resolution"
                       command="SetSubsampleResolution"
                       number_of_elements="1"
                       default_values="-1.">
      <Documentation>
      Subsample points.
      </Documentation>
    </DoubleVectorProperty>

    <DoubleVectorProperty name="Removal outlier radius"
                       command="SetRemovalOutlierRadius"
                       number_of_elements="1"
                       default_values="0.1">
      <Documentation>
      The search radius to remove outlier.
      </Documentation>
    </DoubleVectorProperty>

    <IntVectorProperty name="Removal outlier neighbors"
                       command="SetRemovalOutlierNeighbors"
                       number_of_elements="1"
                       default_values="10">
      <Documentation>
      The number of neighbors that a point must have within the specified radius. Otherwise, the point will be removed.
      </Documentation>
    </IntVectorProperty>

    <PropertyGroup label="Motion estimation Parameters">
      <Property name="Detection Range" />
      <Property name="Azimuth resolution" />
      <Property name="Vertical resolution" />
      <Property name="Initialization time"/>
      <Property name="Window size" />
      <Property name="Subsample range" />
      <Property name="Subsample resolution" />
      <Property name="Removal outlier radius" />
      <Property name="Removal outlier neighbors" />
    </PropertyGroup>

    <!-- ============================ Clustering and tracking ============================ -->
      <IntVectorProperty name="Cluster extractor"
                         command="SetClusterExtractor"
                         number_of_elements="1"
                         default_values="0">
        <EnumerationDomain name="enum">
          <Entry value="0" text="No extraction"/>
          <Entry value="1" text="Euclidean clustering"/>
          <Entry value="2" text="Gaussian mixture model"/>
        </EnumerationDomain>
        <Documentation>
          Choose a extractor for clustering:

           (0) Do not extract clusters;

           (1) Euclidean clustering;

           (2) Gaussian mixture model
        </Documentation>
      </IntVectorProperty>

    <DoubleVectorProperty name="Cluster radius"
                       command="SetClusterRadius"
                       number_of_elements="1"
                       default_values="0.4">
      <Hints>
        <PropertyWidgetDecorator type="GenericDecorator" mode="visibility" inverse="1" property="Cluster extractor" value="0" />
      </Hints>
      <Documentation>
      The search radius to find cluster.
      </Documentation>
    </DoubleVectorProperty>

    <IntVectorProperty name="Cluster minimum point number"
                       command="SetClusterMinNbPoints"
                       number_of_elements="1"
                       default_values="10">
      <Hints>
        <PropertyWidgetDecorator type="GenericDecorator" mode="visibility" inverse="1" property="Cluster extractor" value="0" />
      </Hints>
      <Documentation>
      The number of neighbors that a point must have within the specified radius. Otherwise, the point will be removed.
      </Documentation>
    </IntVectorProperty>

    <IntVectorProperty name="Set tracking window sizes"
                       command="SetTrackingWindowSizes"
                       number_of_elements="1"
                       default_values="10">
      <Documentation>

      </Documentation>
      <Hints>
        <PropertyWidgetDecorator type="GenericDecorator" mode="visibility" property="Cluster extractor" value="2" />
      </Hints>
    </IntVectorProperty>

    <PropertyGroup label="Clustering and tracking Parameters">
      <Property name="Cluster extractor" />
      <Property name="Cluster radius" />
      <Property name="Cluster minimum point number" />
      <Property name="Set tracking window sizes" />
    </PropertyGroup>

    </SourceProxy>
  </ProxyGroup>
  <!-- End MotionDetector -->
</ServerManagerConfiguration>